amplitude/__init__.py
amplitude/logger.py
amplitude_logger-1.0.0.dist-info/METADATA
amplitude_logger-1.0.0.dist-info/WHEEL
amplitude_logger-1.0.0.dist-info/top_level.txt
amplitude_logger-1.0.0.dist-info/RECORD
