Metadata-Version: 2.1
Name: amplitude-logger
Version: 1.0.0
Summary: Amplitude API v2 logger for Python
Home-page: https://github.com/zagran/amplitude-logger
Author: Serhii Zahranychnyi
Author-email: zagranlab@gmail.com
License: UNKNOWN
Platform: UNKNOWN
Classifier: Programming Language :: Python :: 3
Classifier: License :: OSI Approved :: MIT License
Classifier: Operating System :: OS Independent
Requires-Python: >=3.6
Requires-Dist: requests (==2.22.0)
